stateagent/__init__.py
stateagent/core/agent.py
stateagent/core/llm.py
stateagent/core/state.py
stateagent/core/tools.py
stateagent/core/validation.py
stateagent-0.1.0.dist-info/licenses/LICENSE
stateagent-0.1.0.dist-info/METADATA
stateagent-0.1.0.dist-info/WHEEL
stateagent-0.1.0.dist-info/top_level.txt
stateagent-0.1.0.dist-info/RECORD
