Metadata-Version: 2.4
Name: stateagent
Version: 0.1.0
Summary: A library for building reliable, state-driven LLM workflows using the State+CRUD pattern
Home-page: https://github.com/shreyaskal3/stateagent
Author: Shreyas Kale
Author-email: Shreyas Kale <shreyaskale11@gmail.com>
License-Expression: MIT
Project-URL: Homepage, https://github.com/shreyaskal3/stateagent
Project-URL: Repository, https://github.com/shreyaskal3/stateagent
Keywords: llm,ai,chatbot,structured,state-machine,crud,openai
Classifier: Development Status :: 3 - Alpha
Classifier: Intended Audience :: Developers
Classifier: Programming Language :: Python :: 3
Classifier: Programming Language :: Python :: 3.8
Classifier: Programming Language :: Python :: 3.9
Classifier: Programming Language :: Python :: 3.10
Classifier: Programming Language :: Python :: 3.11
Classifier: Programming Language :: Python :: 3.12
Classifier: Topic :: Software Development :: Libraries :: Python Modules
Classifier: Topic :: Scientific/Engineering :: Artificial Intelligence
Requires-Python: >=3.8
License-File: LICENSE
Requires-Dist: openai>=1.0.0
Requires-Dist: dataclasses; python_version < "3.7"
Provides-Extra: dev
Requires-Dist: pytest>=7.0.0; extra == "dev"
Requires-Dist: pytest-cov>=4.0.0; extra == "dev"
Requires-Dist: black>=22.0.0; extra == "dev"
Requires-Dist: isort>=5.0.0; extra == "dev"
Requires-Dist: flake8>=5.0.0; extra == "dev"
Requires-Dist: mypy>=1.0.0; extra == "dev"
Provides-Extra: examples
Requires-Dist: python-dotenv>=1.0.0; extra == "examples"
Dynamic: author
Dynamic: home-page
Dynamic: license-file
Dynamic: requires-python
